cryspy_editor/__init__.py
cryspy_editor/__main__.py
cryspy_editor/ceditor.py
cryspy_editor/cl_thread.py
cryspy_editor/main.pyw
cryspy_editor/f_icon/__init__.py
cryspy_editor/f_icon/calc.gif
cryspy_editor/f_icon/calc_rcif.png
cryspy_editor/f_icon/flip.png
cryspy_editor/f_icon/graph.png
cryspy_editor/f_icon/icon.png
cryspy_editor/f_icon/logo.png
cryspy_editor/f_icon/new.png
cryspy_editor/f_icon/open.png
cryspy_editor/f_icon/open_folder.png
cryspy_editor/f_icon/pm.gif
cryspy_editor/f_icon/refresh.png
cryspy_editor/f_icon/save.png
cryspy_editor/f_icon/save_.png
cryspy_editor/f_icon/save_as.png
cryspy_editor/f_icon/save_as_.png
cryspy_editor/f_icon/to_cryspy.png
cryspy_editor/f_icon/to_cryspy_.png
cryspy_editor/f_icon/to_magref.png
cryspy_editor/f_icon/to_mem.png
cryspy_editor/f_icon/to_rhochi.png
cryspy_editor/f_icon/to_rhochi_.png
cryspy_editor/f_icon/to_star.png
cryspy_editor/f_icon/to_star_.png
cryspy_editor/widgets/__init__.py
cryspy_editor/widgets/cryspy_objects.py
cryspy_editor/widgets/matplotlib.py
cryspy_editor/widgets/ui_setting.py
cryspy_editor/widgets/w_editcif.py
cryspy_editor/widgets/w_function.py
cryspy_editor/widgets/w_object_panel.py
cryspy_editor/widgets/w_texedit.py
cryspy_editor-1.8.0.dist-info/licenses/LICENSE
cryspy_editor-1.8.0.dist-info/METADATA
cryspy_editor-1.8.0.dist-info/WHEEL
cryspy_editor-1.8.0.dist-info/top_level.txt
cryspy_editor-1.8.0.dist-info/RECORD
