Metadata-Version: 2.4
Name: cryspy_editor
Version: 1.8.0
Summary: Editor of CRYSPY files
Home-page:  
Author: Iurii Kibalin
Author-email: yurikibalin@outlook.com
License: MIT License
Keywords: STAR,CrysPy,RhoChi,MEM
Classifier: Programming Language :: Python :: 3
Classifier: Programming Language :: Python :: 3.5
Classifier: Programming Language :: Python :: 3.6
Classifier: Programming Language :: Python :: 3.7
Classifier: Programming Language :: Python :: 3.8
Classifier: Programming Language :: Python :: 3.9
Classifier: Programming Language :: Python :: 3.10
Classifier: Programming Language :: Python :: 3.11
Classifier: Operating System :: OS Independent
License-File: LICENSE
Requires-Dist: cryspy
Requires-Dist: pyqt5
Dynamic: author
Dynamic: author-email
Dynamic: classifier
Dynamic: home-page
Dynamic: keywords
Dynamic: license
Dynamic: license-file
Dynamic: requires-dist
Dynamic: summary
